KlebLib/__init__.py
KlebLib/baseconversion.py
KlebLib/fraction.py
KlebLib/polynomial.py
KlebLib/rounding.py
KlebLib/series.py
KlebLib/test.py
KlebLib/tree.py
KlebLib/universaladdition.py
KlebLib-1.0.2.dist-info/LICENSE
KlebLib-1.0.2.dist-info/METADATA
KlebLib-1.0.2.dist-info/WHEEL
KlebLib-1.0.2.dist-info/top_level.txt
KlebLib-1.0.2.dist-info/RECORD
