Metadata-Version: 2.1
Name: KlebLib
Version: 1.0.2
Summary: A collection of classes and functions that no-one will ever need.
Home-page: https://github.com/Spartan2909/KlebLib/
Author: Caleb Robson
Author-email: robson.caleb.299@gmail.com
License: MIT
Platform: UNKNOWN
Requires-Python: >=3.8, <4
License-File: LICENSE
